scn/__init__.py
scn/scn.py
scn-3.0.1.dist-info/LICENSE.txt
scn-3.0.1.dist-info/METADATA
scn-3.0.1.dist-info/WHEEL
scn-3.0.1.dist-info/top_level.txt
scn-3.0.1.dist-info/RECORD
