Metadata-Version: 2.2
Name: scn
Version: 3.0.1
Home-page: https://github.com/sapiens-technology/SCN
Author: SAPIENS TECHNOLOGY
License: Proprietary Software
License-File: LICENSE.txt
Requires-Dist: torch
Requires-Dist: tiktoken
Requires-Dist: numpy
Requires-Dist: ijson
Requires-Dist: psutil
Requires-Dist: scnetwork
Requires-Dist: hurnet-torch
Requires-Dist: requests
Requires-Dist: tqdm
Dynamic: author
Dynamic: home-page
Dynamic: license
Dynamic: requires-dist
